{"frames": {

"2245.jpg":
{
	"frame": {"x":0,"y":0,"w":630,"h":360},
	"rotated": false,
	"trimmed": false,
	"spriteSourceSize": {"x":0,"y":0,"w":630,"h":360},
	"sourceSize": {"w":630,"h":360}
},
"2246.jpg":
{
	"frame": {"x":630,"y":0,"w":630,"h":360},
	"rotated": false,
	"trimmed": false,
	"spriteSourceSize": {"x":0,"y":0,"w":630,"h":360},
	"sourceSize": {"w":630,"h":360}
},
"2247.jpg":
{
	"frame": {"x":1260,"y":0,"w":630,"h":360},
	"rotated": false,
	"trimmed": false,
	"spriteSourceSize": {"x":0,"y":0,"w":630,"h":360},
	"sourceSize": {"w":630,"h":360}
},
"2248.jpg":
{
	"frame": {"x":1890,"y":0,"w":630,"h":360},
	"rotated": false,
	"trimmed": false,
	"spriteSourceSize": {"x":0,"y":0,"w":630,"h":360},
	"sourceSize": {"w":630,"h":360}
},
"2249.jpg":
{
	"frame": {"x":2520,"y":0,"w":630,"h":360},
	"rotated": false,
	"trimmed": false,
	"spriteSourceSize": {"x":0,"y":0,"w":630,"h":360},
	"sourceSize": {"w":630,"h":360}
},
"2250.jpg":
{
	"frame": {"x":3150,"y":0,"w":630,"h":360},
	"rotated": false,
	"trimmed": false,
	"spriteSourceSize": {"x":0,"y":0,"w":630,"h":360},
	"sourceSize": {"w":630,"h":360}
},
"2251.jpg":
{
	"frame": {"x":0,"y":360,"w":630,"h":360},
	"rotated": false,
	"trimmed": false,
	"spriteSourceSize": {"x":0,"y":0,"w":630,"h":360},
	"sourceSize": {"w":630,"h":360}
},
"2252.jpg":
{
	"frame": {"x":630,"y":360,"w":630,"h":360},
	"rotated": false,
	"trimmed": false,
	"spriteSourceSize": {"x":0,"y":0,"w":630,"h":360},
	"sourceSize": {"w":630,"h":360}
},
"2253.jpg":
{
	"frame": {"x":1260,"y":360,"w":630,"h":360},
	"rotated": false,
	"trimmed": false,
	"spriteSourceSize": {"x":0,"y":0,"w":630,"h":360},
	"sourceSize": {"w":630,"h":360}
},
"2254.jpg":
{
	"frame": {"x":1890,"y":360,"w":630,"h":360},
	"rotated": false,
	"trimmed": false,
	"spriteSourceSize": {"x":0,"y":0,"w":630,"h":360},
	"sourceSize": {"w":630,"h":360}
},
"2255.jpg":
{
	"frame": {"x":2520,"y":360,"w":630,"h":360},
	"rotated": false,
	"trimmed": false,
	"spriteSourceSize": {"x":0,"y":0,"w":630,"h":360},
	"sourceSize": {"w":630,"h":360}
},
"2256.jpg":
{
	"frame": {"x":3150,"y":360,"w":630,"h":360},
	"rotated": false,
	"trimmed": false,
	"spriteSourceSize": {"x":0,"y":0,"w":630,"h":360},
	"sourceSize": {"w":630,"h":360}
},
"2257.jpg":
{
	"frame": {"x":0,"y":720,"w":630,"h":360},
	"rotated": false,
	"trimmed": false,
	"spriteSourceSize": {"x":0,"y":0,"w":630,"h":360},
	"sourceSize": {"w":630,"h":360}
},
"2258.jpg":
{
	"frame": {"x":630,"y":720,"w":630,"h":360},
	"rotated": false,
	"trimmed": false,
	"spriteSourceSize": {"x":0,"y":0,"w":630,"h":360},
	"sourceSize": {"w":630,"h":360}
},
"2259.jpg":
{
	"frame": {"x":1260,"y":720,"w":630,"h":360},
	"rotated": false,
	"trimmed": false,
	"spriteSourceSize": {"x":0,"y":0,"w":630,"h":360},
	"sourceSize": {"w":630,"h":360}
},
"2260.jpg":
{
	"frame": {"x":1890,"y":720,"w":630,"h":360},
	"rotated": false,
	"trimmed": false,
	"spriteSourceSize": {"x":0,"y":0,"w":630,"h":360},
	"sourceSize": {"w":630,"h":360}
},
"2261.jpg":
{
	"frame": {"x":2520,"y":720,"w":630,"h":360},
	"rotated": false,
	"trimmed": false,
	"spriteSourceSize": {"x":0,"y":0,"w":630,"h":360},
	"sourceSize": {"w":630,"h":360}
},
"2262.jpg":
{
	"frame": {"x":3150,"y":720,"w":630,"h":360},
	"rotated": false,
	"trimmed": false,
	"spriteSourceSize": {"x":0,"y":0,"w":630,"h":360},
	"sourceSize": {"w":630,"h":360}
},
"2263.jpg":
{
	"frame": {"x":0,"y":1080,"w":630,"h":360},
	"rotated": false,
	"trimmed": false,
	"spriteSourceSize": {"x":0,"y":0,"w":630,"h":360},
	"sourceSize": {"w":630,"h":360}
},
"2264.jpg":
{
	"frame": {"x":630,"y":1080,"w":630,"h":360},
	"rotated": false,
	"trimmed": false,
	"spriteSourceSize": {"x":0,"y":0,"w":630,"h":360},
	"sourceSize": {"w":630,"h":360}
},
"2265.jpg":
{
	"frame": {"x":1260,"y":1080,"w":630,"h":360},
	"rotated": false,
	"trimmed": false,
	"spriteSourceSize": {"x":0,"y":0,"w":630,"h":360},
	"sourceSize": {"w":630,"h":360}
},
"2266.jpg":
{
	"frame": {"x":1890,"y":1080,"w":630,"h":360},
	"rotated": false,
	"trimmed": false,
	"spriteSourceSize": {"x":0,"y":0,"w":630,"h":360},
	"sourceSize": {"w":630,"h":360}
},
"2267.jpg":
{
	"frame": {"x":2520,"y":1080,"w":630,"h":360},
	"rotated": false,
	"trimmed": false,
	"spriteSourceSize": {"x":0,"y":0,"w":630,"h":360},
	"sourceSize": {"w":630,"h":360}
},
"2268.jpg":
{
	"frame": {"x":3150,"y":1080,"w":630,"h":360},
	"rotated": false,
	"trimmed": false,
	"spriteSourceSize": {"x":0,"y":0,"w":630,"h":360},
	"sourceSize": {"w":630,"h":360}
},
"2269.jpg":
{
	"frame": {"x":0,"y":1440,"w":630,"h":360},
	"rotated": false,
	"trimmed": false,
	"spriteSourceSize": {"x":0,"y":0,"w":630,"h":360},
	"sourceSize": {"w":630,"h":360}
},
"2270.jpg":
{
	"frame": {"x":630,"y":1440,"w":630,"h":360},
	"rotated": false,
	"trimmed": false,
	"spriteSourceSize": {"x":0,"y":0,"w":630,"h":360},
	"sourceSize": {"w":630,"h":360}
},
"2271.jpg":
{
	"frame": {"x":1260,"y":1440,"w":630,"h":360},
	"rotated": false,
	"trimmed": false,
	"spriteSourceSize": {"x":0,"y":0,"w":630,"h":360},
	"sourceSize": {"w":630,"h":360}
},
"2272.jpg":
{
	"frame": {"x":1890,"y":1440,"w":630,"h":360},
	"rotated": false,
	"trimmed": false,
	"spriteSourceSize": {"x":0,"y":0,"w":630,"h":360},
	"sourceSize": {"w":630,"h":360}
},
"2273.jpg":
{
	"frame": {"x":2520,"y":1440,"w":630,"h":360},
	"rotated": false,
	"trimmed": false,
	"spriteSourceSize": {"x":0,"y":0,"w":630,"h":360},
	"sourceSize": {"w":630,"h":360}
},
"2274.jpg":
{
	"frame": {"x":3150,"y":1440,"w":630,"h":360},
	"rotated": false,
	"trimmed": false,
	"spriteSourceSize": {"x":0,"y":0,"w":630,"h":360},
	"sourceSize": {"w":630,"h":360}
},
"2275.jpg":
{
	"frame": {"x":0,"y":1800,"w":630,"h":360},
	"rotated": false,
	"trimmed": false,
	"spriteSourceSize": {"x":0,"y":0,"w":630,"h":360},
	"sourceSize": {"w":630,"h":360}
},
"2276.jpg":
{
	"frame": {"x":630,"y":1800,"w":630,"h":360},
	"rotated": false,
	"trimmed": false,
	"spriteSourceSize": {"x":0,"y":0,"w":630,"h":360},
	"sourceSize": {"w":630,"h":360}
},
"2277.jpg":
{
	"frame": {"x":1260,"y":1800,"w":630,"h":360},
	"rotated": false,
	"trimmed": false,
	"spriteSourceSize": {"x":0,"y":0,"w":630,"h":360},
	"sourceSize": {"w":630,"h":360}
},
"2278.jpg":
{
	"frame": {"x":1890,"y":1800,"w":630,"h":360},
	"rotated": false,
	"trimmed": false,
	"spriteSourceSize": {"x":0,"y":0,"w":630,"h":360},
	"sourceSize": {"w":630,"h":360}
},
"2279.jpg":
{
	"frame": {"x":2520,"y":1800,"w":630,"h":360},
	"rotated": false,
	"trimmed": false,
	"spriteSourceSize": {"x":0,"y":0,"w":630,"h":360},
	"sourceSize": {"w":630,"h":360}
},
"2280.jpg":
{
	"frame": {"x":3150,"y":1800,"w":630,"h":360},
	"rotated": false,
	"trimmed": false,
	"spriteSourceSize": {"x":0,"y":0,"w":630,"h":360},
	"sourceSize": {"w":630,"h":360}
},
"2281.jpg":
{
	"frame": {"x":0,"y":2160,"w":630,"h":360},
	"rotated": false,
	"trimmed": false,
	"spriteSourceSize": {"x":0,"y":0,"w":630,"h":360},
	"sourceSize": {"w":630,"h":360}
},
"2282.jpg":
{
	"frame": {"x":630,"y":2160,"w":630,"h":360},
	"rotated": false,
	"trimmed": false,
	"spriteSourceSize": {"x":0,"y":0,"w":630,"h":360},
	"sourceSize": {"w":630,"h":360}
},
"2283.jpg":
{
	"frame": {"x":1260,"y":2160,"w":630,"h":360},
	"rotated": false,
	"trimmed": false,
	"spriteSourceSize": {"x":0,"y":0,"w":630,"h":360},
	"sourceSize": {"w":630,"h":360}
},
"2284.jpg":
{
	"frame": {"x":1890,"y":2160,"w":630,"h":360},
	"rotated": false,
	"trimmed": false,
	"spriteSourceSize": {"x":0,"y":0,"w":630,"h":360},
	"sourceSize": {"w":630,"h":360}
},
"2285.jpg":
{
	"frame": {"x":2520,"y":2160,"w":630,"h":360},
	"rotated": false,
	"trimmed": false,
	"spriteSourceSize": {"x":0,"y":0,"w":630,"h":360},
	"sourceSize": {"w":630,"h":360}
},
"2286.jpg":
{
	"frame": {"x":3150,"y":2160,"w":630,"h":360},
	"rotated": false,
	"trimmed": false,
	"spriteSourceSize": {"x":0,"y":0,"w":630,"h":360},
	"sourceSize": {"w":630,"h":360}
},
"2287.jpg":
{
	"frame": {"x":0,"y":2520,"w":630,"h":360},
	"rotated": false,
	"trimmed": false,
	"spriteSourceSize": {"x":0,"y":0,"w":630,"h":360},
	"sourceSize": {"w":630,"h":360}
},
"2288.jpg":
{
	"frame": {"x":630,"y":2520,"w":630,"h":360},
	"rotated": false,
	"trimmed": false,
	"spriteSourceSize": {"x":0,"y":0,"w":630,"h":360},
	"sourceSize": {"w":630,"h":360}
},
"2289.jpg":
{
	"frame": {"x":1260,"y":2520,"w":630,"h":360},
	"rotated": false,
	"trimmed": false,
	"spriteSourceSize": {"x":0,"y":0,"w":630,"h":360},
	"sourceSize": {"w":630,"h":360}
},
"2290.jpg":
{
	"frame": {"x":1890,"y":2520,"w":630,"h":360},
	"rotated": false,
	"trimmed": false,
	"spriteSourceSize": {"x":0,"y":0,"w":630,"h":360},
	"sourceSize": {"w":630,"h":360}
},
"2291.jpg":
{
	"frame": {"x":2520,"y":2520,"w":630,"h":360},
	"rotated": false,
	"trimmed": false,
	"spriteSourceSize": {"x":0,"y":0,"w":630,"h":360},
	"sourceSize": {"w":630,"h":360}
},
"2292.jpg":
{
	"frame": {"x":3150,"y":2520,"w":630,"h":360},
	"rotated": false,
	"trimmed": false,
	"spriteSourceSize": {"x":0,"y":0,"w":630,"h":360},
	"sourceSize": {"w":630,"h":360}
},
"2293.jpg":
{
	"frame": {"x":0,"y":2880,"w":630,"h":360},
	"rotated": false,
	"trimmed": false,
	"spriteSourceSize": {"x":0,"y":0,"w":630,"h":360},
	"sourceSize": {"w":630,"h":360}
},
"2294.jpg":
{
	"frame": {"x":630,"y":2880,"w":630,"h":360},
	"rotated": false,
	"trimmed": false,
	"spriteSourceSize": {"x":0,"y":0,"w":630,"h":360},
	"sourceSize": {"w":630,"h":360}
},
"2295.jpg":
{
	"frame": {"x":1260,"y":2880,"w":630,"h":360},
	"rotated": false,
	"trimmed": false,
	"spriteSourceSize": {"x":0,"y":0,"w":630,"h":360},
	"sourceSize": {"w":630,"h":360}
},
"2296.jpg":
{
	"frame": {"x":1890,"y":2880,"w":630,"h":360},
	"rotated": false,
	"trimmed": false,
	"spriteSourceSize": {"x":0,"y":0,"w":630,"h":360},
	"sourceSize": {"w":630,"h":360}
},
"2297.jpg":
{
	"frame": {"x":2520,"y":2880,"w":630,"h":360},
	"rotated": false,
	"trimmed": false,
	"spriteSourceSize": {"x":0,"y":0,"w":630,"h":360},
	"sourceSize": {"w":630,"h":360}
},
"2298.jpg":
{
	"frame": {"x":3150,"y":2880,"w":630,"h":360},
	"rotated": false,
	"trimmed": false,
	"spriteSourceSize": {"x":0,"y":0,"w":630,"h":360},
	"sourceSize": {"w":630,"h":360}
},
"2299.jpg":
{
	"frame": {"x":0,"y":3240,"w":630,"h":360},
	"rotated": false,
	"trimmed": false,
	"spriteSourceSize": {"x":0,"y":0,"w":630,"h":360},
	"sourceSize": {"w":630,"h":360}
},
"2300.jpg":
{
	"frame": {"x":630,"y":3240,"w":630,"h":360},
	"rotated": false,
	"trimmed": false,
	"spriteSourceSize": {"x":0,"y":0,"w":630,"h":360},
	"sourceSize": {"w":630,"h":360}
},
"2301.jpg":
{
	"frame": {"x":1260,"y":3240,"w":630,"h":360},
	"rotated": false,
	"trimmed": false,
	"spriteSourceSize": {"x":0,"y":0,"w":630,"h":360},
	"sourceSize": {"w":630,"h":360}
},
"2302.jpg":
{
	"frame": {"x":1890,"y":3240,"w":630,"h":360},
	"rotated": false,
	"trimmed": false,
	"spriteSourceSize": {"x":0,"y":0,"w":630,"h":360},
	"sourceSize": {"w":630,"h":360}
},
"2303.jpg":
{
	"frame": {"x":2520,"y":3240,"w":630,"h":360},
	"rotated": false,
	"trimmed": false,
	"spriteSourceSize": {"x":0,"y":0,"w":630,"h":360},
	"sourceSize": {"w":630,"h":360}
},
"2304.jpg":
{
	"frame": {"x":3150,"y":3240,"w":630,"h":360},
	"rotated": false,
	"trimmed": false,
	"spriteSourceSize": {"x":0,"y":0,"w":630,"h":360},
	"sourceSize": {"w":630,"h":360}
},
"2305.jpg":
{
	"frame": {"x":0,"y":3600,"w":630,"h":360},
	"rotated": false,
	"trimmed": false,
	"spriteSourceSize": {"x":0,"y":0,"w":630,"h":360},
	"sourceSize": {"w":630,"h":360}
},
"2306.jpg":
{
	"frame": {"x":630,"y":3600,"w":630,"h":360},
	"rotated": false,
	"trimmed": false,
	"spriteSourceSize": {"x":0,"y":0,"w":630,"h":360},
	"sourceSize": {"w":630,"h":360}
},
"2307.jpg":
{
	"frame": {"x":1260,"y":3600,"w":630,"h":360},
	"rotated": false,
	"trimmed": false,
	"spriteSourceSize": {"x":0,"y":0,"w":630,"h":360},
	"sourceSize": {"w":630,"h":360}
},
"2308.jpg":
{
	"frame": {"x":1890,"y":3600,"w":630,"h":360},
	"rotated": false,
	"trimmed": false,
	"spriteSourceSize": {"x":0,"y":0,"w":630,"h":360},
	"sourceSize": {"w":630,"h":360}
},
"2309.jpg":
{
	"frame": {"x":2520,"y":3600,"w":630,"h":360},
	"rotated": false,
	"trimmed": false,
	"spriteSourceSize": {"x":0,"y":0,"w":630,"h":360},
	"sourceSize": {"w":630,"h":360}
},
"2310.jpg":
{
	"frame": {"x":3150,"y":3600,"w":630,"h":360},
	"rotated": false,
	"trimmed": false,
	"spriteSourceSize": {"x":0,"y":0,"w":630,"h":360},
	"sourceSize": {"w":630,"h":360}
}},
"meta": {
	"app": "https://www.codeandweb.com/texturepacker",
	"version": "1.0",
	"image": "Atlas35.png",
	"format": "RGBA8888",
	"size": {"w":3780,"h":3960},
	"scale": "1",
	"smartupdate": "$TexturePacker:SmartUpdate:1e64bf527d4c57cf97345de15e522927:477874635df3294175015926cb9f4645:1a704995cac88e8724577a57d4a254fb$"
}
}
